pyprint_cleaner/__init__.py
pyprint_cleaner/comment_prints.py
pyprint_cleaner/uncomment_prints.py
pyprint_cleaner-1.2.5.dist-info/licenses/LICENSE
pyprint_cleaner-1.2.5.dist-info/METADATA
pyprint_cleaner-1.2.5.dist-info/WHEEL
pyprint_cleaner-1.2.5.dist-info/entry_points.txt
pyprint_cleaner-1.2.5.dist-info/top_level.txt
pyprint_cleaner-1.2.5.dist-info/RECORD
