Metadata-Version: 2.4
Name: pyprint-cleaner
Version: 1.2.5
Summary: A simple tool to comment or uncomment all print() statements in Python projects.
Author: Syed Rakesh Uddin
License: MIT
Project-URL: Homepage, https://github.com/syedrakesh/pyprint-cleaner
Project-URL: Repository, https://github.com/syedrakesh/pyprint-cleaner
Keywords: print,cleanup,comment,automation,devtool
Requires-Python: >=3.7
License-File: LICENSE
Dynamic: license-file
